tests/__init__.py
tests/test_utils.py
tests/test_xml.py
tests/input_files/Case600h10.dck
tests/input_files/TYPE24.bmp
tests/input_files/TYPE24.xml
tests/input_files/Type106.bmp
tests/input_files/Type106.xml
tests/input_files/Type107-simplified.bmp
tests/input_files/Type107-simplified.xml
tests/input_files/Type114.bmp
tests/input_files/Type114.xml
tests/input_files/Type11f.bmp
tests/input_files/Type11f.xml
tests/input_files/Type11h.bmp
tests/input_files/Type11h.xml
tests/input_files/Type146.xml
tests/input_files/Type14h.xml
tests/input_files/Type15-2.bmp
tests/input_files/Type15-2.xml
tests/input_files/Type15-3.bmp
tests/input_files/Type15-3.xml
tests/input_files/Type15-6.bmp
tests/input_files/Type15-6.xml
tests/input_files/Type158.bmp
tests/input_files/Type158.xml
tests/input_files/Type165.bmp
tests/input_files/Type165.xml
tests/input_files/Type1b.bmp
tests/input_files/Type1b.xml
tests/input_files/Type25c.bmp
tests/input_files/Type25c.xml
tests/input_files/Type2b.bmp
tests/input_files/Type2b.xml
tests/input_files/Type2d.bmp
tests/input_files/Type2d.xml
tests/input_files/Type39.xml
tests/input_files/Type41c.xml
tests/input_files/Type46a.xml
tests/input_files/Type47a.xml
tests/input_files/Type48b.xml
tests/input_files/Type4a.xml
tests/input_files/Type50d.xml
tests/input_files/Type647.bmp
tests/input_files/Type647.xml
tests/input_files/Type65c.bmp
tests/input_files/Type65c.xml
tests/input_files/Type65d.bmp
tests/input_files/Type65d.xml
tests/input_files/Type951.bmp
tests/input_files/Type951.xml
tests/input_files/Type9c.bmp
tests/input_files/Type9c.xml
tests/input_files/test_deck.dck
tests/input_files/tpfs/Type951.dck
tests/input_files/tpfs/Type951.tpf
trnsystor/__init__.py
trnsystor/anchorpoint.py
trnsystor/canvas.py
trnsystor/component.py
trnsystor/controlcards.py
trnsystor/deck.py
trnsystor/externalfile.py
trnsystor/linkstyle.py
trnsystor/name.py
trnsystor/run.py
trnsystor/specialcard.py
trnsystor/studio.py
trnsystor/trnsysmodel.py
trnsystor/typecycle.py
trnsystor-1.4.1.dist-info/LICENSE.md
trnsystor-1.4.1.dist-info/METADATA
trnsystor-1.4.1.dist-info/WHEEL
trnsystor-1.4.1.dist-info/top_level.txt
trnsystor-1.4.1.dist-info/RECORD
