Metadata-Version: 2.1
Name: trnsystor
Version: 1.4.1
Summary: A python TRNSYS type parser
Home-page: https://github.com/samuelduchesne/trnsystor
Author: Samuel Letellier-Duchesne
Author-email: samuel.letellier-duchesne@polymtl.ca
License: MIT
Keywords: TRNSYS type XML proforma
Platform: UNKNOWN
Classifier: Development Status :: 4 - Beta
Classifier: Intended Audience :: Science/Research
Classifier: License :: OSI Approved :: MIT License
Classifier: Programming Language :: Python :: 3.7
Classifier: Programming Language :: Python :: 3.8
Classifier: Programming Language :: Python :: 3.9
Requires-Dist: outdated (~=0.2.1)
Requires-Dist: pint (~=0.17)
Requires-Dist: tabulate (~=0.8.9)
Requires-Dist: path (~=15.1.2)
Requires-Dist: shapely (~=1.7.1)
Requires-Dist: numpy (~=1.20.3)
Requires-Dist: matplotlib (~=3.4.2)
Requires-Dist: pandas (~=1.2.4)
Requires-Dist: sympy (==1.5.*)
Requires-Dist: beautifulsoup4 (~=4.9.3)
Requires-Dist: lxml (~=4.6.3)
Provides-Extra: dev
Requires-Dist: pytest ; extra == 'dev'
Requires-Dist: mock ; extra == 'dev'
Requires-Dist: pytest-cov ; extra == 'dev'
Requires-Dist: coverage ; extra == 'dev'
Requires-Dist: coveralls ; extra == 'dev'
Requires-Dist: sphinx (>=2.1) ; extra == 'dev'
Requires-Dist: networkx ; extra == 'dev'
Requires-Dist: recommonmark ; extra == 'dev'
Requires-Dist: sphinx-rtd-theme ; extra == 'dev'
Requires-Dist: pytest-xdist ; extra == 'dev'
